pbar/__init__.py
pbar/bar.py
pbar/cond.py
pbar/gen.py
pbar/sets.py
pbar/task_wrapper.py
pbar/utils.py
PBar2-2.2.2.dist-info/LICENSE
PBar2-2.2.2.dist-info/METADATA
PBar2-2.2.2.dist-info/WHEEL
PBar2-2.2.2.dist-info/top_level.txt
PBar2-2.2.2.dist-info/RECORD
