Metadata-Version: 2.1
Name: PBar2
Version: 2.2.2
Summary: Display customizable progress bars on the terminal easily.
Home-page: https://darvil82.github.io/PBar
Author: David Losantos (DarviL82)
Author-email: davidlosantos89@gmail.com
License: UNKNOWN
Project-URL: Tracker, https://github.com/DarviL82/PBar/issues
Project-URL: Documentation, https://github.com/DarviL82/PBar/wiki
Platform: UNKNOWN
Classifier: Programming Language :: Python :: 3
Classifier: Programming Language :: Python :: 3.9
Classifier: Programming Language :: Python :: 3.10
Classifier: License :: OSI Approved :: MIT License
Classifier: Operating System :: OS Independent
Requires-Python: >=3.9
License-File: LICENSE
